json_pydantic/__init__.py
json_pydantic/__main__.py
json_pydantic/classes.py
json_pydantic/conventer.py
json_pydantic/functions.py
json_pydantic/variables.py
json_pydantic-1.1.0.dist-info/LICENCE
json_pydantic-1.1.0.dist-info/METADATA
json_pydantic-1.1.0.dist-info/WHEEL
json_pydantic-1.1.0.dist-info/entry_points.txt
json_pydantic-1.1.0.dist-info/top_level.txt
json_pydantic-1.1.0.dist-info/RECORD
