Metadata-Version: 2.1
Name: json-pydantic
Version: 1.1.0
Summary: Utility for converting json files to Pydantic models
Home-page: https://github.com/temkuz/json_pydantic
Author: temkuz
Author-email: temkuz@yandex.ru
License-File: LICENCE
Requires-Dist: Jinja2 (==3.1.2)
